Metadata-Version: 1.0
Name: logging-telegram
Version: 0.1.0
Summary: Telegram logging handler
Home-page: UNKNOWN
Author: Artiom Rotari
Author-email: artiom.rotari@ebs-integrator.com
License: UNKNOWN
Platform: UNKNOWN
